MagicPanel/__init__.py
MagicPanel-0.1.2.dist-info/LICENSE
MagicPanel-0.1.2.dist-info/METADATA
MagicPanel-0.1.2.dist-info/WHEEL
MagicPanel-0.1.2.dist-info/top_level.txt
MagicPanel-0.1.2.dist-info/RECORD
