Metadata-Version: 2.1
Name: MagicPanel
Version: 0.1.2
Summary: A useful package to standardize, merge, and optimize panel data sets.
Home-page: https://pypi.org/project/MagicPanel
Author: Yifan Zhang
Author-email: zyfcode@outlook.com
Classifier: Programming Language :: Python :: 3
Classifier: License :: OSI Approved :: GNU General Public License v3 (GPLv3)
Classifier: Operating System :: OS Independent
Requires-Python: >=3.6
License-File: LICENSE
